leuci_geo/__init__.py
leuci_geo/geocalculator.py
leuci_geo/pdbgeometry.py
leuci_geo/pdbloader.py
leuci_geo/pdbobject.py
leuci_geo/pdbspace.py
leuci_geo/reportmaker.py
leuci_geo-0.0.9.dist-info/LICENSE
leuci_geo-0.0.9.dist-info/METADATA
leuci_geo-0.0.9.dist-info/WHEEL
leuci_geo-0.0.9.dist-info/top_level.txt
leuci_geo-0.0.9.dist-info/RECORD
